geoquiz/csv/selected_names.csv
geoquiz/images_noaxis/Afghanistan.png
geoquiz/images_noaxis/Akrotiri.png
geoquiz/images_noaxis/Albania.png
geoquiz/images_noaxis/Algeria.png
geoquiz/images_noaxis/American Samoa.png
geoquiz/images_noaxis/Andorra.png
geoquiz/images_noaxis/Angola.png
geoquiz/images_noaxis/Anguilla.png
geoquiz/images_noaxis/Antigua and Barbuda.png
geoquiz/images_noaxis/Argentina.png
geoquiz/images_noaxis/Armenia.png
geoquiz/images_noaxis/Aruba.png
geoquiz/images_noaxis/Ashmore and Cartier Is..png
geoquiz/images_noaxis/Australia.png
geoquiz/images_noaxis/Austria.png
geoquiz/images_noaxis/Azerbaijan.png
geoquiz/images_noaxis/Bahrain.png
geoquiz/images_noaxis/Baikonur.png
geoquiz/images_noaxis/Bajo Nuevo Bank.png
geoquiz/images_noaxis/Bangladesh.png
geoquiz/images_noaxis/Barbados.png
geoquiz/images_noaxis/Belarus.png
geoquiz/images_noaxis/Belgium.png
geoquiz/images_noaxis/Belize.png
geoquiz/images_noaxis/Benin.png
geoquiz/images_noaxis/Bermuda.png
geoquiz/images_noaxis/Bhutan.png
geoquiz/images_noaxis/Bir Tawil.png
geoquiz/images_noaxis/Bolivia.png
geoquiz/images_noaxis/Bosnia and Herzegovina.png
geoquiz/images_noaxis/Botswana.png
geoquiz/images_noaxis/Brazil.png
geoquiz/images_noaxis/Brazilian I..png
geoquiz/images_noaxis/British Virgin Is..png
geoquiz/images_noaxis/Brunei.png
geoquiz/images_noaxis/Bulgaria.png
geoquiz/images_noaxis/Burkina Faso.png
geoquiz/images_noaxis/Burundi.png
geoquiz/images_noaxis/Cambodia.png
geoquiz/images_noaxis/Cameroon.png
geoquiz/images_noaxis/Canada.png
geoquiz/images_noaxis/Cape Verde.png
geoquiz/images_noaxis/Cayman Is..png
geoquiz/images_noaxis/Central African Republic.png
geoquiz/images_noaxis/Chad.png
geoquiz/images_noaxis/Chile.png
geoquiz/images_noaxis/Colombia.png
geoquiz/images_noaxis/Comoros.png
geoquiz/images_noaxis/Congo.png
geoquiz/images_noaxis/Cook Is..png
geoquiz/images_noaxis/Coral Sea Is..png
geoquiz/images_noaxis/Costa Rica.png
geoquiz/images_noaxis/Croatia.png
geoquiz/images_noaxis/Cuba.png
geoquiz-0.1.7.dist-info/LICENSE
geoquiz-0.1.7.dist-info/METADATA
geoquiz-0.1.7.dist-info/WHEEL
geoquiz-0.1.7.dist-info/entry_points.txt
geoquiz-0.1.7.dist-info/RECORD
