Metadata-Version: 2.1
Name: geoquiz
Version: 0.1.7
Summary: A game where you have
License: MIT
Author: amrutha-b-nair
Author-email: amruthabn00@gmail.com
Requires-Python: >=3.10,<4.0
Classifier: License :: OSI Approved :: MIT License
Classifier: Programming Language :: Python :: 3
Classifier: Programming Language :: Python :: 3.10
Classifier: Programming Language :: Python :: 3.11
Classifier: Programming Language :: Python :: 3.12
Requires-Dist: fuzzywuzzy (>=0.18.0,<0.19.0)
Requires-Dist: pillow (>=10.1.0,<11.0.0)
Requires-Dist: pygame (>=2.5.2,<3.0.0)
